[{"img":"img/home/shopp/op1.jpg"},{"subtitle":"享8折","img":"img/home/shopp/op2.jpg","title":"小米路由器 青春版","explain":"11月1日0点-24点 特价59元","saleprice":"59元","price":"79元"},{"subtitle":"享8折","img":"img/home/shopp/op3.jpg","title":"小米路由器","explain":"11月1日0点-24点 特价99元","saleprice":"99元","price":"129元"},{"subtitle":"享9折","img":"img/home/shopp/op4.jpg","title":"米家小白智能摄像机","explain":"11月1日0点-24点 特价349元","saleprice":"349元","price":"399元"},{"subtitle":"享8折","img":"img/home/shopp/op5.jpg","title":"米家压力IH电饭煲","explain":"11月1日0点-24点 特价899元","saleprice":"899元","price":"999元"},{"subtitle":"","img":"img/home/shopp/op6.jpg","title":"九号平衡车","explain":"年轻人的酷玩具 骑行遥控两种玩法","saleprice":"1999元","price":""},{"subtitle":"","img":"img/home/shopp/op7.jpg","title":"米家飞利浦睿智台灯二代","explain":"感知环境光 主动优化场景照明","saleprice":"199元","price":""},{"subtitle":"免邮费","img":"img/home/shopp/op8.jpg","title":"小米手环 2","explain":"每天早10点开售","saleprice":"149元","price":""},{"subtitle":"免邮费","img":"img/home/shopp/op9.jpg","title":"米家iHealth血压计","explain":"感知环境光 主动优化场景照明","saleprice":"399元","price":""}] 